tagish/__init__.py
tagish/__main__.py
tagish/api.py
tagish/deserialize.py
tagish/rules.py
tagish/serialize.py
tagish-1.0.0.dist-info/METADATA
tagish-1.0.0.dist-info/WHEEL
tagish-1.0.0.dist-info/entry_points.txt
tagish-1.0.0.dist-info/RECORD
