Metadata-Version: 2.3
Name: tagish
Version: 1.0.0
Summary: A gerernic tag format for serialization deserializatio
License: MIT
Author: adebert
Author-email: debert@gmail.com
Requires-Python: >=3.13
Classifier: License :: OSI Approved :: MIT License
Classifier: Programming Language :: Python :: 3
Classifier: Programming Language :: Python :: 3.13
